pioreactor/__init__.py
pioreactor/config.py
pioreactor/error_codes.py
pioreactor/exc.py
pioreactor/hardware.py
pioreactor/json_log_formatter.py
pioreactor/logging.py
pioreactor/models.py
pioreactor/mureq.py
pioreactor/pubsub.py
pioreactor/py.typed
pioreactor/states.py
pioreactor/structs.py
pioreactor/types.py
pioreactor/version.py
pioreactor/whoami.py
pioreactor/actions/__init__.py
pioreactor/actions/led_intensity.py
pioreactor/actions/od_blank.py
pioreactor/actions/pump.py
pioreactor/actions/pumps.py
pioreactor/actions/self_test.py
pioreactor/actions/leader/__init__.py
pioreactor/actions/leader/backup_database.py
pioreactor/actions/leader/experiment_profile.py
pioreactor/actions/leader/export_experiment_data.py
pioreactor/automations/__init__.py
pioreactor/automations/base.py
pioreactor/automations/events.py
pioreactor/automations/dosing/__init__.py
pioreactor/automations/dosing/base.py
pioreactor/automations/dosing/chemostat.py
pioreactor/automations/dosing/fed_batch.py
pioreactor/automations/dosing/pid_morbidostat.py
pioreactor/automations/dosing/silent.py
pioreactor/automations/dosing/turbidostat.py
pioreactor/automations/led/__init__.py
pioreactor/automations/led/base.py
pioreactor/automations/led/light_dark_cycle.py
pioreactor/automations/led/silent.py
pioreactor/automations/temperature/__init__.py
pioreactor/automations/temperature/base.py
pioreactor/automations/temperature/only_record_temperature.py
pioreactor/automations/temperature/thermostat.py
pioreactor/background_jobs/__init__.py
pioreactor/background_jobs/base.py
pioreactor/background_jobs/dosing_automation.py
pioreactor/background_jobs/growth_rate_calculating.py
pioreactor/background_jobs/led_automation.py
pioreactor/background_jobs/monitor.py
pioreactor/background_jobs/od_reading.py
pioreactor/background_jobs/stirring.py
pioreactor/background_jobs/temperature_automation.py
pioreactor/background_jobs/leader/__init__.py
pioreactor/background_jobs/leader/mqtt_to_db_streaming.py
pioreactor-26.1.30.dist-info/METADATA
pioreactor-26.1.30.dist-info/WHEEL
pioreactor-26.1.30.dist-info/entry_points.txt
pioreactor-26.1.30.dist-info/top_level.txt
pioreactor-26.1.30.dist-info/RECORD
